API_CHANGES
Changelog
FAQ
KNOWN_BUGS
LICENSE_data
LICENSE_geos
MANIFEST.in
nad2bin.c
setup.py
geos-3.3.3/.gitignore
geos-3.3.3/AUTHORS
geos-3.3.3/CMakeLists.txt
geos-3.3.3/COPYING
geos-3.3.3/ChangeLog
geos-3.3.3/INSTALL
geos-3.3.3/Makefile.am
geos-3.3.3/Makefile.in
geos-3.3.3/NEWS
geos-3.3.3/README
geos-3.3.3/TODO
geos-3.3.3/aclocal.m4
geos-3.3.3/acsite.m4
geos-3.3.3/autogen.bat
geos-3.3.3/config.guess
geos-3.3.3/config.sub
geos-3.3.3/configure
geos-3.3.3/configure.in
geos-3.3.3/depcomp
geos-3.3.3/install-sh
geos-3.3.3/ltmain.sh
geos-3.3.3/makefile.vc
geos-3.3.3/missing
geos-3.3.3/nmake.opt
geos-3.3.3/py-compile
geos-3.3.3/capi/CMakeLists.txt
geos-3.3.3/capi/Makefile.am
geos-3.3.3/capi/Makefile.in
geos-3.3.3/capi/geos_c.cpp
geos-3.3.3/capi/geos_c.h
geos-3.3.3/capi/geos_c.h.in
geos-3.3.3/capi/geos_ts_c.cpp
geos-3.3.3/cmake/cmake_uninstall.cmake.in
geos-3.3.3/cmake/modules/COPYING-CMAKE-SCRIPTS
geos-3.3.3/cmake/modules/CheckPrototypeExists.cmake
geos-3.3.3/doc/Doxyfile
geos-3.3.3/doc/Doxyfile.in
geos-3.3.3/doc/Makefile.am
geos-3.3.3/doc/Makefile.in
geos-3.3.3/doc/README
geos-3.3.3/doc/example.cpp
geos-3.3.3/include/CMakeLists.txt
geos-3.3.3/include/Makefile.am
geos-3.3.3/include/Makefile.in
geos-3.3.3/include/config.h.in
geos-3.3.3/include/geos.h
geos-3.3.3/include/geos/Makefile.am
geos-3.3.3/include/geos/Makefile.in
geos-3.3.3/include/geos/export.h
geos-3.3.3/include/geos/geom.h
geos-3.3.3/include/geos/geomUtil.h
geos-3.3.3/include/geos/geomgraph.h
geos-3.3.3/include/geos/geomgraphindex.h
geos-3.3.3/include/geos/geosAlgorithm.h
geos-3.3.3/include/geos/indexBintree.h
geos-3.3.3/include/geos/indexChain.h
geos-3.3.3/include/geos/indexQuadtree.h
geos-3.3.3/include/geos/indexStrtree.h
geos-3.3.3/include/geos/indexSweepline.h
geos-3.3.3/include/geos/inline.h
geos-3.3.3/include/geos/io.h
geos-3.3.3/include/geos/noding.h
geos-3.3.3/include/geos/nodingSnapround.h
geos-3.3.3/include/geos/opBuffer.h
geos-3.3.3/include/geos/opDistance.h
geos-3.3.3/include/geos/opLinemerge.h
lib/base_atlas.egg-info/PKG-INFO
lib/base_atlas.egg-info/SOURCES.txt
lib/base_atlas.egg-info/dependency_links.txt
lib/base_atlas.egg-info/namespace_packages.txt
lib/base_atlas.egg-info/requires.txt
lib/base_atlas.egg-info/top_level.txt
