Metadata-Version: 1.1
Name: base-atlas
Version: 1.2.0
Summary: Plot data on map projections with matplotlib
Home-page: http://matplotlib.org/basemap/
Author: Ben Root
Author-email: ben.v.root@gmail.com
License: OSI Approved
Download-URL: https://github.com/matplotlib/basemap/archive/v1.2.0rel.tar.gz
Keywords: python,plotting,plots,graphs,charts,GIS,mapping,map projections,maps
Platform: any
Classifier: Development Status :: 5 - Production/Stable
Classifier: Intended Audience :: Science/Research
Classifier: License :: OSI Approved
Classifier: Programming Language :: Python
Classifier: Programming Language :: Python :: 3
Classifier: Topic :: Scientific/Engineering :: Visualization
Classifier: Topic :: Software Development :: Libraries :: Python Modules
Classifier: Operating System :: OS Independent
